djradicale/__init__.py
djradicale/admin.py
djradicale/auth.py
djradicale/config.py
djradicale/models.py
djradicale/rights.py
djradicale/storage.py
djradicale/urls.py
djradicale/views.py
djradicale/migrations/0001_initial.py
djradicale/migrations/__init__.py
djradicale/tests/__init__.py
djradicale/tests/test_caldav.py
djradicale/tests/test_carddav.py
djradicale/tests/test_serialize.py
django_radicale-0.0.17.dist-info/LICENSE
django_radicale-0.0.17.dist-info/METADATA
django_radicale-0.0.17.dist-info/WHEEL
django_radicale-0.0.17.dist-info/top_level.txt
django_radicale-0.0.17.dist-info/RECORD
