Metadata-Version: 2.1
Name: django-radicale
Version: 0.0.17
Summary: Integration of Radicale with Django
Home-page: https://github.com/kyokenn/djradicale
Author: Kyoken
Author-email: Kyoken <kyoken@kyoken.ninja>
License: GPLv3
Project-URL: Source, https://github.com/kyokenn/djradicale
Keywords: django radicale carddav caldav
Classifier: Programming Language :: Python :: 3
Classifier: License :: OSI Approved :: GNU General Public License v3 (GPLv3)
Classifier: Operating System :: OS Independent
Requires-Python: >=3.10
License-File: LICENSE
Requires-Dist: Django >=4.0.1
Requires-Dist: Radicale >=3.1.2
